nsystems/__init__.py
nsystems/nsystems.py
nsystems-0.4.0.dist-info/LICENSE
nsystems-0.4.0.dist-info/METADATA
nsystems-0.4.0.dist-info/WHEEL
nsystems-0.4.0.dist-info/top_level.txt
nsystems-0.4.0.dist-info/RECORD
