Metadata-Version: 2.1
Name: nsystems
Version: 0.4.0
Summary: Convert numbers between different numeral systems.
Home-page: UNKNOWN
Author: nsystems
Author-email: nsystems.module@gmail.com
License: MIT
Keywords: number,systems,system,base,base64,base32,basen,convert,number systems,number system,binary,hexadecimal,octal,decimal
Platform: UNKNOWN
License-File: LICENSE
